nonebot_plugin_xinghuo_api/__init__.py
nonebot_plugin_xinghuo_api/config.py
nonebot_plugin_xinghuo_api-2.4.0.dist-info/METADATA
nonebot_plugin_xinghuo_api-2.4.0.dist-info/WHEEL
nonebot_plugin_xinghuo_api-2.4.0.dist-info/RECORD
