Metadata-Version: 2.1
Name: nonebot-plugin-xinghuo-api
Version: 2.4.0
Summary: A nonebot plugin for xinghuo LLM
License: MIT
Author: Alpaca
Author-email: admin@alpaca.kim
Requires-Python: >=3.8,<4.0
Classifier: License :: OSI Approved :: MIT License
Classifier: Programming Language :: Python :: 3
Classifier: Programming Language :: Python :: 3.8
Classifier: Programming Language :: Python :: 3.9
Classifier: Programming Language :: Python :: 3.10
Classifier: Programming Language :: Python :: 3.11
Classifier: Programming Language :: Python :: 3.12
Classifier: Programming Language :: Python :: 3.13
Requires-Dist: nonebot-adapter-onebot (>=2.2.1,<3.0.0)
Requires-Dist: nonebot2 (>=2.0.0rc3,<3.0.0)
Requires-Dist: spark_ai_python (>=0.4.4,<0.5.0)
Requires-Dist: websocket-client (>=1.6.1,<2.0.0)
